accountandtransactionapispecification/__init__.py
accountandtransactionapispecification/accountandtransactionapispecification_client.py
accountandtransactionapispecification/api_helper.py
accountandtransactionapispecification/configuration.py
accountandtransactionapispecification/controllers/__init__.py
accountandtransactionapispecification/controllers/accounts_controller.py
accountandtransactionapispecification/controllers/balances_controller.py
accountandtransactionapispecification/controllers/base_controller.py
accountandtransactionapispecification/controllers/beneficiaries_controller.py
accountandtransactionapispecification/controllers/direct_debits_controller.py
accountandtransactionapispecification/controllers/offers_controller.py
accountandtransactionapispecification/controllers/party_controller.py
accountandtransactionapispecification/controllers/scheduled_payments_controller.py
accountandtransactionapispecification/controllers/standing_orders_controller.py
accountandtransactionapispecification/controllers/statements_controller.py
accountandtransactionapispecification/controllers/transactions_controller.py
accountandtransactionapispecification/exceptions/__init__.py
accountandtransactionapispecification/exceptions/accounts_400_error_exception.py
accountandtransactionapispecification/exceptions/accounts_403_error_exception.py
accountandtransactionapispecification/exceptions/accounts_500_error_exception.py
accountandtransactionapispecification/exceptions/accounts_503_error_exception.py
accountandtransactionapispecification/exceptions/accounts_balances_400_error_exception.py
accountandtransactionapispecification/exceptions/accounts_balances_403_error_exception.py
accountandtransactionapispecification/exceptions/accounts_balances_500_error_exception.py
accountandtransactionapispecification/exceptions/accounts_balances_503_error_exception.py
accountandtransactionapispecification/exceptions/accounts_beneficiaries_400_error_exception.py
pnz_payments_sdk-1.0.0.dist-info/licenses/LICENSE
pnz_payments_sdk-1.0.0.dist-info/METADATA
pnz_payments_sdk-1.0.0.dist-info/WHEEL
pnz_payments_sdk-1.0.0.dist-info/top_level.txt
pnz_payments_sdk-1.0.0.dist-info/RECORD
