Metadata-Version: 2.4
Name: pnz-payments-sdk
Version: 1.0.0
Summary: PNZ Payments Account and Transaction API
Author-email: developer sdksio <developer+sdksio@apimatic.io>
Project-URL: Documentation, https://pnz-app.azurewebsites.net/
Keywords: PNZ,Payments,sdksio,API,APIMatic,Payment Newzealand
Requires-Python: >=3.7
License-File: LICENSE
Requires-Dist: apimatic-core>=0.2.17,~=0.2.0
Requires-Dist: apimatic-core-interfaces>=0.1.5,~=0.1.0
Requires-Dist: apimatic-requests-client-adapter>=0.1.6,~=0.1.0
Provides-Extra: testutils
Requires-Dist: pytest>=7.2.2; extra == "testutils"
Dynamic: license-file
